core_authorizer/__init__.py
core_authorizer/get_permissions.py
core_logging/__init__.py
core_logging/aws_logging.py
vitor_core_test-1.0.1.dist-info/LICENSE
vitor_core_test-1.0.1.dist-info/METADATA
vitor_core_test-1.0.1.dist-info/WHEEL
vitor_core_test-1.0.1.dist-info/top_level.txt
vitor_core_test-1.0.1.dist-info/RECORD
