Metadata-Version: 2.1
Name: vitor-core-test
Version: 1.0.1
Summary: Vitor test core
License: BSD 3-Clause License
Keywords: unimed,core
Classifier: License :: OSI Approved :: BSD License
Classifier: Programming Language :: Python :: 3
License-File: LICENSE
Requires-Dist: requests
Requires-Dist: pyjwt (>=2.4)
